guesslang/__init__.py
guesslang/__main__.py
guesslang/guess.py
guesslang/model.py
guesslang/data/languages.json
guesslang/data/model/saved_model.pb
guesslang/data/model/variables/variables.data-00000-of-00001
guesslang/data/model/variables/variables.index
guesslang_experimental-2.2.3.dist-info/LICENSE
guesslang_experimental-2.2.3.dist-info/METADATA
guesslang_experimental-2.2.3.dist-info/WHEEL
guesslang_experimental-2.2.3.dist-info/entry_points.txt
guesslang_experimental-2.2.3.dist-info/top_level.txt
guesslang_experimental-2.2.3.dist-info/RECORD
